looksee/__init__.py
looksee/scanner.py
looksee-3.0.4.dist-info/LICENSE
looksee-3.0.4.dist-info/METADATA
looksee-3.0.4.dist-info/WHEEL
looksee-3.0.4.dist-info/top_level.txt
looksee-3.0.4.dist-info/RECORD
