Metadata-Version: 2.1
Name: looksee
Version: 3.0.4
Summary: Looksee walks python modules in the file system, scans them, and executes a custom callback for each object that matches a logical predicate.  This is a less annoying alternative to Venusian scanner.
Home-page: https://github.com/gigaquads/looksee.git
Author: Gigaquads
Author-email: what@gigaquads.com
License: UNKNOWN
Platform: UNKNOWN
Classifier: Programming Language :: Python :: 3.9
Classifier: License :: OSI Approved :: MIT License
Requires-Dist: appyratus
